dockerr/__init__.py
dockerr/py.typed
dockerr/runner.py
dockerr/utils/__init__.py
dockerr/utils/container.py
dockerr/utils/docker.py
dockerr/utils/py.typed
dockerr-0.2.1.dist-info/LICENSE
dockerr-0.2.1.dist-info/METADATA
dockerr-0.2.1.dist-info/WHEEL
dockerr-0.2.1.dist-info/top_level.txt
dockerr-0.2.1.dist-info/RECORD
